{
  "hud_screen@screen_jexp.screen": {
    "is_showing_menu": false,
    "should_steal_mouse": true,
    "low_frequency_rendering": true,
    "absorbs_input": false,
    "send_telemetry": false,
    "button_mappings": [
      { "from_button_id": "button.scoreboard",
        "to_button_id": "button.scoreboard",
        "mapping_type": "global"
      },
      { "from_button_id": "button.inventory_left",
        "to_button_id": "button.hotbar_inventory_left",
        "mapping_type": "global"
      },
      { "from_button_id": "button.inventory_right",
        "to_button_id": "button.hotbar_inventory_right",
        "mapping_type": "global"
      },
      { "from_button_id": "button.hide_gui",
        "to_button_id": "button.hide_gui_all",
        "mapping_type": "global"
      },
      { "from_button_id": "button.hide_tooltips",
        "to_button_id": "button.hide_tooltips_hud",
        "mapping_type": "global"
      },
      { "from_button_id": "button.hide_paperdoll",
        "to_button_id": "button.hide_paperdoll_hud",
        "mapping_type": "global"
      },
      { "from_button_id": "button.slot1",
        "to_button_id": "button.slot_1",
        "mapping_type": "global"
      },
      { "from_button_id": "button.slot2",
        "to_button_id": "button.slot_2",
        "mapping_type": "global"
      },
      { "from_button_id": "button.slot3",
        "to_button_id": "button.slot_3",
        "mapping_type": "global"
      },
      { "from_button_id": "button.slot4",
        "to_button_id": "button.slot_4",
        "mapping_type": "global"
      },
      { "from_button_id": "button.slot5",
        "to_button_id": "button.slot_5",
        "mapping_type": "global"
      },
      { "from_button_id": "button.slot6",
        "to_button_id": "button.slot_6",
        "mapping_type": "global"
      },
      { "from_button_id": "button.slot7",
        "to_button_id": "button.slot_7",
        "mapping_type": "global"
      },
      { "from_button_id": "button.slot8",
        "to_button_id": "button.slot_8",
        "mapping_type": "global"
      },
      { "from_button_id": "button.slot9",
        "to_button_id": "button.slot_9",
        "mapping_type": "global"
      },
      { "from_button_id": "button.slot0",
        "to_button_id": "button.slot_0",
        "mapping_type": "global"
      }
    ],
    "render_only_when_topmost": false,
    "$scrn_cont": "ingame_hud.screen_content"
  }/* ,

  "hud_actionbar_text": {
    "type": "image",
    "size": [ "100%c + 12px", "100%c + 5px" ],
    "offset": [-1, 1],
    "anchor_from": "top_right",
    "anchor_to": "top_right",
    "texture": "textures/ui/hud_tip_text_background",
    "alpha": "@hud.anim_actionbar_text_background_alpha_out",
    "controls": [
      {
        "actionbar_message": {
          "type": "label",
          "anchor_from": "center",
          "anchor_to": "center",
          "color": "$tool_tip_text",
          "layer": 1,
          "text": "$actionbar_text",
          "localize": false,
          "alpha": "@hud.anim_actionbar_text_alpha_out"
        }
      }
    ]
  } */
}